beepy_app_template_example/main.py
beepy_app_template_example-0.1.0.dist-info/LICENSE
beepy_app_template_example-0.1.0.dist-info/METADATA
beepy_app_template_example-0.1.0.dist-info/WHEEL
beepy_app_template_example-0.1.0.dist-info/entry_points.txt
beepy_app_template_example-0.1.0.dist-info/RECORD
