Metadata-Version: 2.1
Name: beepy_app_template_example
Version: 0.1.0
Summary: An example of the output you get when creating a new beepy app from the cookiecutter template.
Home-page: https://github.com/conor-f/beepy-app-template-example
License: GPLv3
Author: conor-f
Author-email: beepy@randombits.host
Requires-Python: >=3.9,<4.0
Classifier: License :: Other/Proprietary License
Classifier: Programming Language :: Python :: 3
Classifier: Programming Language :: Python :: 3.9
Classifier: Programming Language :: Python :: 3.10
Classifier: Programming Language :: Python :: 3.11
Classifier: Programming Language :: Python :: 3.12
Classifier: Programming Language :: Python :: 3.13
Requires-Dist: textual (>=0.82.0,<0.83.0)
